{"categories_sj": [{"title": "FAMOUS NAMES", "clues": ["0-0", "0-1", "0-2", "0-3", "0-4"]}, {"title": "THE BEATLES", "clues": ["1-0", "1-1", "1-2", "1-3", "1-4"]}, {"title": "COLORS", "clues": ["2-0", "2-1", "2-2", "2-3", "2-4"]}, {"title": "THE MOVIES", "clues": ["3-0", "3-1", "3-2", "3-3", "3-4"]}, {"title": "COUNTRIES OF THE WORLD", "clues": ["4-0", "4-1", "4-2", "4-3", "4-4"]}, {"title": "LEFTOVERS", "clues": ["5-0", "5-1", "5-2", "5-3", "5-4"]}], "categories_dj": [{"title": "INVENTORS", "clues": ["0-0", "0-1", "0-2", "0-3", "0-4"]}, {"title": "QUOTATIONS", "clues": ["1-0", "1-1", "1-2", "1-3", "1-4"]}, {"title": "AMERICANA", "clues": ["2-0", "2-1", "2-2", "2-3", "2-4"]}, {"title": "1881", "clues": ["3-0", "3-1", "3-2", "3-3", "3-4"]}, {"title": "THEATRE", "clues": ["4-0", "4-1", "4-2", "4-3", "4-4"]}, {"title": "IT'S EXTINCT", "clues": ["5-0", "5-1", "5-2", "5-3", "5-4"]}], "categories_fj": [{"title": "DEMOCRATS", "clues": ["0-0"]}], "clues_sj": {"0-0": {"question": "2 months before his own death, Robert Kennedy attended the funeral of this slain civil rights leader", "answer": "Martin Luther King", "value": 200, "is_dd": false}, "1-0": {"question": "The oldest Beatle, this drummer was the last to join the group", "answer": "Ringo Starr", "value": 200, "is_dd": false}, "2-0": {"question": "Fire-engine is a bright shade of this color", "answer": "red", "value": 200, "is_dd": false}, "3-0": {"question": "In 1995 Bruce Willis returned to the screen \"With a Vengeance\" in the 2nd sequel to this film", "answer": "Die Hard", "value": 200, "is_dd": false}, "4-0": {"question": "Most of this Mediterranean country's population lives along the Nile Valley", "answer": "Egypt", "value": 200, "is_dd": false}, "5-0": {"question": "As the old saying goes, \"What's sauce for the goose\" is this", "answer": "sauce for the gander", "value": 200, "is_dd": false}, "0-1": {"question": "In December 1994 he announced his retirement & the closing of his institute founded with Virginia Johnson", "answer": "(William) Masters", "value": 400, "is_dd": false}, "1-1": {"question": "After seeing his son Julian's drawing of a school friend named Lucy, John wrote this song", "answer": "\"Lucy In The Sky With Diamonds\"", "value": 400, "is_dd": false}, "2-1": {"question": "It's a light yellowish brown, or the shade you turn after bathing in the sun", "answer": "tan", "value": 400, "is_dd": false}, "3-1": {"question": "In this 1967 drama, Sidney Poitier preferred to be called Mr. Tibbs", "answer": "In the Heat of the Night", "value": 400, "is_dd": false}, "4-1": {"question": "The northern third of this grand duchy is an extension of the Belgian Ardennes", "answer": "Luxembourg", "value": 400, "is_dd": false}, "5-1": {"question": "This first lady broke a champagne bottle across the bow of the Nautilus submarine January 21, 1954", "answer": "Mamie Eisenhower", "value": 400, "is_dd": false}, "0-2": {"question": "This fashion designer named his company \"Polo\" because it suggested class & elegance", "answer": "Ralph Lauren", "value": 600, "is_dd": false}, "1-2": {"question": "Br!an Epstein's former assistant Wendy Hanson needed releases from all living people on this 1967 album cover", "answer": "Sgt. Pepper\\'s Lonely Hearts Club Band", "value": 600, "is_dd": false}, "2-2": {"question": "Named for the Irish town, Killarney is a shade of this color", "answer": "green", "value": 600, "is_dd": false}, "3-2": {"question": "Completes the title of the Hugh Grant film \"The Englishman who Went Up a Hill but...\"", "answer": "Came down a Mountain", "value": 600, "is_dd": false}, "4-2": {"question": "The Kathmandu Valley is a flat basin in the center of this country,", "answer": "Nepal", "value": 600, "is_dd": false}, "5-2": {"question": "This aircraft company built the Bulldog, Pup & Snipe as well as the Camel", "answer": "Sopwith", "value": 600, "is_dd": false}, "0-3": {"question": "He taught chemistry for several years at Notre Dame before becoming head football coach in 1918", "answer": "Knute Rockne", "value": 800, "is_dd": false}, "1-3": {"question": "It \"leads to your door\"", "answer": "\"The Long And Winding Road\"", "value": 800, "is_dd": false}, "2-3": {"question": "It's used to describe the highest degree \"of perfection\"", "answer": "pink", "value": 800, "is_dd": false}, "3-3": {"question": "Don Ameche & Wilford Brimley were among the senior citizens rejuvenated in this 1985 film", "answer": "Cocoon", "value": 800, "is_dd": false}, "4-3": {"question": "Argos is believed to be the oldest city in this country", "answer": "Greece", "value": 800, "is_dd": false}, "5-3": {"question": "175 papers carry the advice column of this woman who earned her Ph.D. in psychology at Columbia", "answer": "Dr. Joyce Brothers", "value": 800, "is_dd": false}, "0-4": {"question": "The first major Bolshoi Ballet member to defect to the U.S., this dancer turned actor died in 1995 at age 45", "answer": "Alexander Godunov", "value": 1000, "is_dd": false}, "1-4": {"question": "The girl of his dreams \"called herself Lil, but everyone knew her as Nancy\"", "answer": "Rocky Raccoon", "value": 1000, "is_dd": false}, "2-4": {"question": "Nevada's state colors are blue & this; it helps if you know the state nickname", "answer": "silver", "value": 1000, "is_dd": false}, "3-4": {"question": "Jon Voight won an Oscar for his role as a paraplegic war vet in this 1978 film", "answer": "Coming Home", "value": 1000, "is_dd": false}, "4-4": {"question": "Odadahraun, the largest lava bed on Earth, lies on this North Atlantic island nation", "answer": "Iceland", "value": 1000, "is_dd": false}, "5-4": {"question": "He was born August 31, 1908 in Fresno, had \"The Time of his Life\" & died there May 18, 1981", "answer": "William Saroyan", "value": 1000, "is_dd": false}}, "clues_dj": {"0-0": {"question": "Nicolas Appert, who invented canning, got a 12,000-franc reward from this emperor in 1810", "answer": "Napoleon", "value": 400, "is_dd": false}, "1-0": {"question": "W.S. Gilbert wrote, \"In for a penny, in for\" this, \"It's love that makes the world go round!\"", "answer": "a pound", "value": 400, "is_dd": false}, "2-0": {"question": "The Maryland Historical Society houses the original manuscript of his \"Star-Spangled Banner\"", "answer": "Francis Scott Key", "value": 400, "is_dd": false}, "3-0": {"question": "Due to charges of indecency, the 6th edition of this Walt Whitman collection was withdrawn from publication", "answer": "Leaves of Grass", "value": 400, "is_dd": false}, "4-0": {"question": "This 1979 play was based on the real-life story of John Merrick, who was exploited for his deformity", "answer": "The Elephant Man", "value": 400, "is_dd": false}, "5-0": {"question": "The Siberian or woolly is by far the best-known form of this extinct elephant", "answer": "the mammoth", "value": 400, "is_dd": false}, "0-1": {"question": "It's said a dream Elias Howe had about men threatening him with spears led to the needle for this invention", "answer": "the sewing machine", "value": 800, "is_dd": false}, "1-1": {"question": "This comedian's signature line is \"I don't get no respect\"", "answer": "Rodney Dangerfield", "value": 800, "is_dd": false}, "2-1": {"question": "A museum in Des Plaines, Illinois traces the history of this fast food chain", "answer": "McDonald\\'s", "value": 800, "is_dd": false}, "3-1": {"question": "This telegraph company bought up several competitors to consolidate its monopoly", "answer": "Western Union", "value": 800, "is_dd": false}, "4-1": {"question": "Kenneth Branaghs \"Public Enemy\" tells of a young man obsessed with this legendary actor", "answer": "James Cagney", "value": 800, "is_dd": false}, "5-1": {"question": "These New Zealand natives might say, \"Please, sir, I want some moa\" since they liked to hunt them", "answer": "the Maoris", "value": 800, "is_dd": false}, "0-2": {"question": "James Dewar, inventor of the Thermos bottle, was also the first to liquefy this lightest gas", "answer": "hydrogen", "value": 1200, "is_dd": false}, "1-2": {"question": "In 1995 her son, Texas' governor, told her, \"Don't brag\"", "answer": "Barbara Bush", "value": 1200, "is_dd": false}, "2-2": {"question": "In 1923 this state adopted the nickname \"The Wonder State\"; in 1953 it became the \"Land of Opportunity\"", "answer": "Arkansas", "value": 1200, "is_dd": false}, "3-2": {"question": "This yachting trophy was won by Mischief, which took 2 races from a Canadian yacht", "answer": "the America\\'s Cup", "value": 1200, "is_dd": false}, "4-2": {"question": "Matthew Broderick rises to the top of the corporate world in the 1995 revival of this musical", "answer": "How to Succeed in Business Without Really Trying", "value": 1200, "is_dd": false}, "5-2": {"question": "The last of these pigeons died in the Cincinnati Zoo in 1914", "answer": "the passenger pigeon", "value": 1200, "is_dd": false}, "0-3": {"question": "Thomas Newcomen's version of this device was a precursor of James Watt's", "answer": "the steam engine", "value": 1600, "is_dd": false}, "1-3": {"question": "Meyer Lansky supposedly said of the syndicate, \"We're bigger than\" this metals company", "answer": "U.S. Steel", "value": 1600, "is_dd": false}, "2-3": {"question": "Named for an explorer, its the oldest continuously inhabited city in Washington State", "answer": "Vancouver", "value": 1600, "is_dd": false}, "3-3": {"question": "This American expatriate exhibited her paintings in France for the third year in a row", "answer": "Mary Cassatt", "value": 1600, "is_dd": false}, "4-3": {"question": "This Arthur Miller play is based on the Salem witch trials of 1692", "answer": "The Crucible", "value": 1600, "is_dd": false}, "5-3": {"question": "The giant, plant-eating Apatosaurus is better known by this name", "answer": "the Brontosaurus", "value": 1600, "is_dd": false}, "0-4": {"question": "This founder of the frozen food industry also invented a technique to speed up food dehydration", "answer": "Birdseye", "value": 2000, "is_dd": false}, "1-4": {"question": "This first Indian prime minister said, \"A life is ordered by values\"", "answer": "Nehru", "value": 2000, "is_dd": false}, "2-4": {"question": "An archive in Plymouth, Vermont has photos, family films & voice recordings of this U.S. president", "answer": "Coolidge", "value": 2000, "is_dd": false}, "3-4": {"question": "On March 4 he was inaugurated as vice president; on September 20, he was sworn in as president", "answer": "Chester Arthur", "value": 2000, "is_dd": false}, "4-4": {"question": "In February 1995 the Off-Broadway \"Wedding\" & reception of this pair celebrated its 7th year on stage", "answer": "Tony n\\' Tina", "value": 2000, "is_dd": false}, "5-4": {"question": "This Danish explorer's expedition found Steller's sea cow in 1741; by 1768 it had been exterminated", "answer": "Bering", "value": 2000, "is_dd": false}}, "clues_fj": {"0-0": {"question": "In 1995 he cast his 14,000th vote in the Senate, a record for any party", "answer": "Senator (Robert) Byrd", "value": 10000, "is_dd": false}}}